zipline/__init__.py
zipline/__main__.py
zipline/_protocol.c
zipline/_protocol.cp310-win_amd64.pyd
zipline/_protocol.html
zipline/_protocol.pxd
zipline/_protocol.pyx
zipline/_version.py
zipline/algorithm.py
zipline/api.py
zipline/api.pyi
zipline/country.py
zipline/currency.py
zipline/dispatch.py
zipline/errors.py
zipline/extensions.py
zipline/protocol.py
zipline/test_algorithms.py
zipline/zipline_warnings.py
zipline/assets/__init__.py
zipline/assets/_assets.c
zipline/assets/_assets.cp310-win_amd64.pyd
zipline/assets/_assets.html
zipline/assets/_assets.pxd
zipline/assets/_assets.pyx
zipline/assets/asset_db_migrations.py
zipline/assets/asset_db_schema.py
zipline/assets/asset_writer.py
zipline/assets/assets.py
zipline/assets/continuous_futures.c
zipline/assets/continuous_futures.cp310-win_amd64.pyd
zipline/assets/continuous_futures.html
zipline/assets/continuous_futures.pyx
zipline/assets/exchange_info.py
zipline/assets/futures.py
zipline/assets/roll_finder.py
zipline/assets/synthetic.py
zipline/data/__init__.py
zipline/data/_adjustments.c
zipline/data/_adjustments.cp310-win_amd64.pyd
zipline/data/_adjustments.html
zipline/data/_adjustments.pyx
zipline/data/_equities.c
zipline/data/_equities.cp310-win_amd64.pyd
zipline/data/_equities.html
zipline/data/_equities.pyx
zipline/data/_minute_bar_internal.c
zipline/data/_minute_bar_internal.cp310-win_amd64.pyd
zipline/data/_minute_bar_internal.html
zipline/data/_minute_bar_internal.pyx
zipline/data/_resample.c
zipline/data/_resample.cp310-win_amd64.pyd
zipline/data/_resample.html
zipline/data/_resample.pyx
zipline/data/adjustments.py
zipline/data/bar_reader.py
zipline/data/bcolz_daily_bars.py
zipline/data/bcolz_minute_bars.py
zipline/data/benchmarks.py
zipline/data/continuous_future_reader.py
zipline/data/data_portal.py
zipline/data/dispatch_bar_reader.py
zipline/data/hdf5_daily_bars.py
zipline/data/history_loader.py
zipline/data/in_memory_daily_bars.py
zipline/data/loader.py
zipline/data/resample.py
zipline_reloaded-3.1.dist-info/AUTHORS
zipline_reloaded-3.1.dist-info/LICENSE
zipline_reloaded-3.1.dist-info/METADATA
zipline_reloaded-3.1.dist-info/WHEEL
zipline_reloaded-3.1.dist-info/entry_points.txt
zipline_reloaded-3.1.dist-info/top_level.txt
zipline_reloaded-3.1.dist-info/RECORD
