Metadata-Version: 2.1
Name: zipline-reloaded
Version: 3.1
Summary: A Pythonic backtester for trading algorithms
Author: Quantopian Inc
Author-email: pm@ml4trading.io
Maintainer: Stefan Jansen
Maintainer-email: pm@ml4trading.io
License: 
Project-URL: homepage, https://ml4trading.io
Project-URL: repository, https://github.com/stefan-jansen/zipline-reloaded
Project-URL: documentation, https://zipline.ml4trading.io
Classifier: Development Status :: 4 - Beta
Classifier: License :: OSI Approved :: Apache Software License
Classifier: Natural Language :: English
Classifier: Programming Language :: Python
Classifier: Programming Language :: Python :: 3.9
Classifier: Programming Language :: Python :: 3.10
Classifier: Programming Language :: Python :: 3.11
Classifier: Programming Language :: Python :: 3.12
Classifier: Operating System :: OS Independent
Classifier: Intended Audience :: Science/Research
Classifier: Topic :: Office/Business :: Financial :: Investment
Classifier: Topic :: Scientific/Engineering :: Information Analysis
Classifier: Topic :: System :: Distributed Computing
Requires-Python: >=3.9
License-File: LICENSE
License-File: AUTHORS
Requires-Dist: pandas<3.0,>=1.3.0
Requires-Dist: alembic>=0.7.7
Requires-Dist: bcolz-zipline>=1.2.6
Requires-Dist: bottleneck>=1.0.0
Requires-Dist: click>=4.0.0
Requires-Dist: empyrical-reloaded>=0.5.7
Requires-Dist: h5py>=2.7.1
Requires-Dist: intervaltree>=2.1.0
Requires-Dist: iso3166>=2.1.1
Requires-Dist: iso4217>=1.6.20180829
Requires-Dist: lru-dict>=1.1.4
Requires-Dist: multipledispatch>=0.6.0
Requires-Dist: networkx>=2.0
Requires-Dist: numexpr>=2.6.1
Requires-Dist: patsy>=0.4.0
Requires-Dist: python-dateutil>=2.4.2
Requires-Dist: python-interface>=1.5.3
Requires-Dist: pytz>=2018.5
Requires-Dist: requests>=2.9.1
Requires-Dist: scipy>=0.17.1
Requires-Dist: six>=1.10.0
Requires-Dist: sqlalchemy>=2
Requires-Dist: statsmodels>=0.6.1
Requires-Dist: tables>=3.4.3
Requires-Dist: toolz>=0.8.2
Requires-Dist: exchange-calendars>=4.2.4
Requires-Dist: numpy<2,>=1.23.5; python_version < "3.10"
Requires-Dist: numpy>=1.23.5; python_version < "3.12"
Requires-Dist: numpy>=1.26.0; python_version >= "3.12"
Provides-Extra: dev
Requires-Dist: flake8>=3.9.1; extra == "dev"
Requires-Dist: black>=24.0b1; extra == "dev"
Requires-Dist: pre-commit>=2.12.1; extra == "dev"
Requires-Dist: Cython>=0.29.21; extra == "dev"
Requires-Dist: ruff; extra == "dev"
Provides-Extra: docs
Requires-Dist: Cython; extra == "docs"
Requires-Dist: Sphinx>=1.3.2; extra == "docs"
Requires-Dist: numpydoc>=0.5.0; extra == "docs"
Requires-Dist: sphinx-autobuild>=0.6.0; extra == "docs"
Requires-Dist: pydata-sphinx-theme; extra == "docs"
Requires-Dist: sphinx-markdown-tables; extra == "docs"
Requires-Dist: m2r2; extra == "docs"
Provides-Extra: test
Requires-Dist: tox; extra == "test"
Requires-Dist: pytest>=7.2.0; extra == "test"
Requires-Dist: pytest-cov>=3.0.0; extra == "test"
Requires-Dist: pytest-xdist>=2.5.0; extra == "test"
Requires-Dist: pytest-timeout>=1.4.2; extra == "test"
Requires-Dist: parameterized>=0.6.1; extra == "test"
Requires-Dist: testfixtures>=4.1.2; extra == "test"
Requires-Dist: flake8>=3.9.1; extra == "test"
Requires-Dist: matplotlib>=1.5.3; extra == "test"
Requires-Dist: responses>=0.9.0; extra == "test"
Requires-Dist: pandas-datareader>=0.2.1; extra == "test"
Requires-Dist: click; extra == "test"
Requires-Dist: coverage; extra == "test"
Requires-Dist: pytest-rerunfailures; extra == "test"
